pds/__init__.py
pds/epitome/VERSION.txt
pds/epitome/__init__.py
pds/epitome/main.py
pds_epitome-3.21.0.dist-info/licenses/LICENSE.md
pds_epitome-3.21.0.dist-info/licenses/NOTICE.txt
pds_epitome-3.21.0.dist-info/METADATA
pds_epitome-3.21.0.dist-info/WHEEL
pds_epitome-3.21.0.dist-info/entry_points.txt
pds_epitome-3.21.0.dist-info/top_level.txt
pds_epitome-3.21.0.dist-info/zip-safe
pds_epitome-3.21.0.dist-info/RECORD
