Metadata-Version: 2.4
Name: pds_epitome
Version: 3.21.0
Summary: A small demonstration of the PDS Python repository template
Home-page: https://github.com/nasa-pds-engineering-node/epitome
Download-URL: https://github.com/nasa-pds-engineering-node/epitome/releases/
Author: PDS
Author-email: pds_operator@jpl.nasa.gov
License: apache-2.0
Keywords: pds,epitome,exemplar,prototype,demonstration,example,exhibit
Classifier: Programming Language :: Python :: 3
Classifier: Programming Language :: Python :: 3.13
Classifier: Operating System :: OS Independent
Requires-Python: >=3.13
License-File: LICENSE.md
License-File: NOTICE.txt
Provides-Extra: dev
Requires-Dist: black~=23.7.0; extra == "dev"
Requires-Dist: flake8~=6.1.0; extra == "dev"
Requires-Dist: flake8-bugbear~=23.7.10; extra == "dev"
Requires-Dist: flake8-docstrings~=1.7.0; extra == "dev"
Requires-Dist: pep8-naming~=0.13.3; extra == "dev"
Requires-Dist: mypy~=1.5.1; extra == "dev"
Requires-Dist: pydocstyle~=6.3.0; extra == "dev"
Requires-Dist: coverage~=7.3.0; extra == "dev"
Requires-Dist: pytest~=7.4.0; extra == "dev"
Requires-Dist: pytest-cov~=4.1.0; extra == "dev"
Requires-Dist: pytest-watch~=4.2.0; extra == "dev"
Requires-Dist: pytest-xdist~=3.3.1; extra == "dev"
Requires-Dist: pre-commit~=3.3.3; extra == "dev"
Requires-Dist: sphinx~=8.2.3; extra == "dev"
Requires-Dist: sphinx-rtd-theme~=3.0.2; extra == "dev"
Requires-Dist: alabaster~=1.0.0; extra == "dev"
Requires-Dist: tox~=4.11.0; extra == "dev"
Requires-Dist: Jinja2~=3.1.6; extra == "dev"
Requires-Dist: sphinxcontrib-googleanalytics~=0.5; extra == "dev"
Dynamic: download-url
Dynamic: license-file
